4-bit ALU Design/Verilog/Codes/andblock.v
module andblock(input [3:0] A,input [3:0] B,output [3:0] C);
  and(C[3],A[3],B[3]);
  and(C[2],A[2],B[2]);
  and(C[1],A[1],B[1]);
  and(C[0],A[0],B[0]);
endmodule

4-bit ALU Design/Verilog/Codes/comparator.v
module comparator(input [3:0] A,input [3:0] B,output greater,output lesser,output equal);
  wire eq0;
  wire eq1;
  wire eq2;
  wire eq3;
  xnor(eq0,A[0],B[0]);
  xnor(eq1,A[1],B[1]);
  xnor(eq2,A[2],B[2]);
  xnor(eq3,A[3],B[3]);

  
  wire [3:0] A_comp;
  wire [3:0] B_comp;
  not(A_comp[3],A[3]);
  not(A_comp[2],A[2]);
  not(A_comp[1],A[1]);
  not(A_comp[0],A[0]);
  not(B_comp[3],B[3]);
  not(B_comp[2],B[2]);
  not(B_comp[1],B[1]);
  not(B_comp[0],B[0]);


  wire greater0;
  wire greater1;
  wire greater2;
  wire greater3;
  and(greater3,A[3],B_comp[3]);
  and(greater2,eq3,A[2],B_comp[2]);
  and(greater1,eq3,eq2,A[1],B_comp[1]);
  and(greater0,eq3,eq2,eq1,A[0],B_comp[0]);

 
  wire lesser0;
  wire lesser1;
  wire lesser2;
  wire lesser3;
  and(lesser3,A_comp[3],B[3]);
  and(lesser2,eq3,A_comp[2],B[2]);
  and(lesser1,eq3,eq2,A_comp[1],B[1]);
  and(lesser0,eq3,eq2,eq1,A_comp[0],B[0]);
  

  and(equal,eq0,eq1,eq2,eq3);
  or(greater,greater0,greater1,greater2,greater3);
  or(lesser,lesser0,lesser1,lesser2,lesser3);


endmodule

4-bit ALU Design/Verilog/Codes/fulladder.v
module fulladder(input A,input B,input C_in,output S,output C);
   wire S_inter;
   wire C_inter1;
   wire C_inter2;
   xor(S_inter,A,B);
   xor(S,S_inter,C_in);
   and(C_inter1,A,B);
   and(C_inter2,S_inter,C_in);
   or(C,C_inter1,C_inter2);

endmodule

4-bit ALU Design/Verilog/Codes/addersubtractor.v
`include "fulladder.v"
module addersubtractor(input M,input [3:0] A,input [3:0] B,output [3:0] S,output carry);
  wire [3:0] B_updated;
  xor(B_updated[3],B[3],M);
  xor(B_updated[2],B[2],M);
  xor(B_updated[1],B[1],M);
  xor(B_updated[0],B[0],M);
  wire C1;
  wire C2;
  wire C3;
  fulladder instance_1(.A(A[0]),.B(B_updated[0]),.C_in(M),.S(S[0]),.C(C1));
  fulladder instance_2(.A(A[1]),.B(B_updated[1]),.C_in(C1),.S(S[1]),.C(C2));
  fulladder instance_3(.A(A[2]),.B(B_updated[2]),.C_in(C2),.S(S[2]),.C(C3));
  fulladder instance_4(.A(A[3]),.B(B_updated[3]),.C_in(C3),.S(S[3]),.C(carry));
  
endmodule

4-bit ALU Design/Verilog/Codes/enableblock.v
module enableblock(input enable,input [3:0] A_in,input [3:0] B_in,output [3:0] A_out,output [3:0] B_out);
  and(A_out[3],A_in[3],enable);
  and(A_out[2],A_in[2],enable);
  and(A_out[1],A_in[1],enable);
   and(A_out[0],A_in[0],enable);
   and(B_out[3],B_in[3],enable);
  and(B_out[2],B_in[2],enable);
  and(B_out[1],B_in[1],enable);
  and(B_out[0],B_in[0],enable);
endmodule

4-bit ALU Design/Verilog/Codes/twotofourdecoder.v
module twotofourdecoder(input S0,input S1,output D0,output D1,output D2,output D3);
  wire S0_comp;
  wire S1_comp;
  not(S0_comp,S0);
  not(S1_comp,S1);
  and(D0,S0_comp,S1_comp);
  and(D1,S0,S1_comp);
  and(D2,S1,S0_comp);
  and(D3,S0,S1);
endmodule

4-bit ALU Design/Verilog/Codes/ALU.v
`include "twotofourdecoder.v"
`include "enableblock.v"
`include "addersubtractor.v"
`include "comparator.v"
`include "andblock.v"
module ALU(input S0,input S1,input [3:0] A,input [3:0] B,output [3:0] S_0,output carry,output greater,output lesser,output equal,output [3:0] S_3 );
   wire D0,D1,D2,D3;
   wire [3:0] A_0;
   wire [3:0] A_2;
   wire [3:0] A_3;
   wire [3:0] B_0;
   wire [3:0] B_2;
   wire [3:0] B_3;
  wire D_updated;
  wire equal_temp;
  wire carry_temp;
  wire carry_temp2;
  twotofourdecoder instance_1(.S0(S0),.S1(S1),.D0(D0),.D1(D1),.D2(D2),.D3(D3));
  or(D_updated,D0,D1);
  enableblock inst_1(.enable(D_updated),.A_in(A),.B_in(B),.A_out(A_0),.B_out(B_0));
  enableblock inst_2(.enable(D2),.A_in(A),.B_in(B),.A_out(A_2),.B_out(B_2));
  enableblock inst_3(.enable(D3),.A_in(A),.B_in(B),.A_out(A_3),.B_out(B_3));
  addersubtractor inst_4(.M(S0),.A(A_0),.B(B_0),.S(S_0),.carry(carry_temp));
  comparator inst_5(.A(A_2),.B(B_2),.greater(greater),.lesser(lesser),.equal(equal_temp));
  andblock inst_6(.A(A_3),.B(B_3),.C(S_3));
  and(equal,equal_temp,D2);
  and(carry_temp2,carry_temp,D_updated);
  xor(carry,carry_temp2,D1);

endmodule

4-bit ALU Design/Verilog/Codes/ALU_tb.v
`include "ALU.v"
module ALU_tb;
  reg [3:0] A;
  reg [3:0] B;
  reg S0,S1;
  wire [3:0] addersubtractor;
  wire carry;
  wire [3:0] And;
  wire greater,lesser,equal;
  ALU DUT(S0,S1,A,B,addersubtractor,carry,greater,lesser,equal,And);
  
  initial begin
    $dumpfile("ALU_tb.vcd");
    $dumpvars(0, ALU_tb);
    S1=1;
    S0=1;
    A=4'b1101;
    B=4'b1001;
    #10
    S1=0;
    S0=1;
    A=4'b0100;
    B=4'b1011;
    #10
    A=4'b0110;
    B=4'b1111;
    #10
    S1=1;
    S0=1;
    A=4'b0110;
    B=4'b1101;
    #10
    S1=1;
    S0=0;
    A=4'b1000;
    B=4'b1000;
    #10
    S1=0;
    S0=0;
    A=4'b1101;
    B=4'b1100;
    #10
    S1=1;
    S0=1;
    A=4'b0000;
    B=4'b0000;
    #10
    S1=0;
    S0=0;
    A=4'b0011;
    B=4'b1100;
    #10
    S1=1;
    S0=1;
    A=4'b1011;
    B=4'b1010;

    #10 $finish; 
  end
  
endmodule

4-bit ALU Design/Verilog/Codes/ALU_tb.vcd
$date
	Tue Nov  7 01:21:34 2023
$end
$version
	Icarus Verilog
$end
$timescale
	1s
$end
$scope module ALU_tb $end
$var wire 1 ! lesser $end
$var wire 1 " greater $end
$var wire 1 # equal $end
$var wire 1 $ carry $end
$var wire 4 % addersubtractor [3:0] $end
$var wire 4 & And [3:0] $end
$var reg 4 ' A [3:0] $end
$var reg 4 ( B [3:0] $end
$var reg 1 ) S0 $end
$var reg 1 * S1 $end
$scope module DUT $end
$var wire 4 + A [3:0] $end
$var wire 4 , B [3:0] $end
$var wire 1 - D_updated $end
$var wire 1 ) S0 $end
$var wire 1 * S1 $end
$var wire 1 $ carry $end
$var wire 1 . carry_temp2 $end
$var wire 1 # equal $end
$var wire 1 ! lesser $end
$var wire 1 " greater $end
$var wire 1 / equal_temp $end
$var wire 1 0 carry_temp $end
$var wire 4 1 S_3 [3:0] $end
$var wire 4 2 S_0 [3:0] $end
$var wire 1 3 D3 $end
$var wire 1 4 D2 $end
$var wire 1 5 D1 $end
$var wire 1 6 D0 $end
$var wire 4 7 B_3 [3:0] $end
$var wire 4 8 B_2 [3:0] $end
$var wire 4 9 B_0 [3:0] $end
$var wire 4 : A_3 [3:0] $end
$var wire 4 ; A_2 [3:0] $end
$var wire 4 < A_0 [3:0] $end
$scope module inst_1 $end
$var wire 4 = A_in [3:0] $end
$var wire 4 > B_in [3:0] $end
$var wire 1 - enable $end
$var wire 4 ? B_out [3:0] $end
$var wire 4 @ A_out [3:0] $end
$upscope $end
$scope module inst_2 $end
$var wire 4 A A_in [3:0] $end
$var wire 4 B B_in [3:0] $end
$var wire 1 4 enable $end
$var wire 4 C B_out [3:0] $end
$var wire 4 D A_out [3:0] $end
$upscope $end
$scope module inst_3 $end
$var wire 4 E A_in [3:0] $end
$var wire 4 F B_in [3:0] $end
$var wire 1 3 enable $end
$var wire 4 G B_out [3:0] $end
$var wire 4 H A_out [3:0] $end
$upscope $end
$scope module inst_4 $end
$var wire 4 I A [3:0] $end
$var wire 4 J B [3:0] $end
$var wire 1 ) M $end
$var wire 1 0 carry $end
$var wire 4 K S [3:0] $end
$var wire 1 L C3 $end
$var wire 1 M C2 $end
$var wire 1 N C1 $end
$var wire 4 O B_updated [3:0] $end
$scope module instance_1 $end
$var wire 1 P A $end
$var wire 1 Q B $end
$var wire 1 N C $end
$var wire 1 ) C_in $end
$var wire 1 R C_inter1 $end
$var wire 1 S C_inter2 $end
$var wire 1 T S $end
$var wire 1 U S_inter $end
$upscope $end
$scope module instance_2 $end
$var wire 1 V A $end
$var wire 1 W B $end
$var wire 1 M C $end
$var wire 1 N C_in $end
$var wire 1 X C_inter1 $end
$var wire 1 Y C_inter2 $end
$var wire 1 Z S $end
$var wire 1 [ S_inter $end
$upscope $end
$scope module instance_3 $end
$var wire 1 \ A $end
$var wire 1 ] B $end
$var wire 1 L C $end
$var wire 1 M C_in $end
$var wire 1 ^ C_inter1 $end
$var wire 1 _ C_inter2 $end
$var wire 1 ` S $end
$var wire 1 a S_inter $end
$upscope $end
$scope module instance_4 $end
$var wire 1 b A $end
$var wire 1 c B $end
$var wire 1 0 C $end
$var wire 1 L C_in $end
$var wire 1 d C_inter1 $end
$var wire 1 e C_inter2 $end
$var wire 1 f S $end
$var wire 1 g S_inter $end
$upscope $end
$upscope $end
$scope module inst_5 $end
$var wire 4 h A [3:0] $end
$var wire 4 i B [3:0] $end
$var wire 1 j eq0 $end
$var wire 1 k eq1 $end
$var wire 1 l eq2 $end
$var wire 1 m eq3 $end
$var wire 1 / equal $end
$var wire 1 " greater $end
$var wire 1 n greater0 $end
$var wire 1 o greater1 $end
$var wire 1 p greater2 $end
$var wire 1 q greater3 $end
$var wire 1 ! lesser $end
$var wire 1 r lesser0 $end
$var wire 1 s lesser1 $end
$var wire 1 t lesser2 $end
$var wire 1 u lesser3 $end
$var wire 4 v B_comp [3:0] $end
$var wire 4 w A_comp [3:0] $end
$upscope $end
$scope module inst_6 $end
$var wire 4 x A [3:0] $end
$var wire 4 y B [3:0] $end
$var wire 4 z C [3:0] $end
$upscope $end
$scope module instance_1 $end
$var wire 1 6 D0 $end
$var wire 1 5 D1 $end
$var wire 1 4 D2 $end
$var wire 1 3 D3 $end
$var wire 1 ) S0 $end
$var wire 1 { S0_comp $end
$var wire 1 * S1 $end
$var wire 1 | S1_comp $end
$upscope $end
$upscope $end
$upscope $end
$enddefinitions $end
#0
$dumpvars
0|
0{
b1001 z
b1001 y
b1101 x
b1111 w
b1111 v
0u
0t
0s
0r
0q
0p
0o
0n
1m
1l
1k
1j
b0 i
b0 h
1g
0f
1e
0d
1c
0b
1a
0`
1_
0^
1]
0\
1[
0Z
1Y
0X
1W
0V
1U
0T
1S
0R
1Q
0P
b1111 O
1N
1M
1L
b0 K
b0 J
b0 I
b1101 H
b1001 G
b1001 F
b1101 E
b0 D
b0 C
b1001 B
b1101 A
b0 @
b0 ?
b1001 >
b1101 =
b0 <
b0 ;
b1101 :
b0 9
b0 8
b1001 7
06
05
04
13
b0 2
b1001 1
10
1/
0.
0-
b1001 ,
b1101 +
1*
1)
b1001 (
b1101 '
b1001 &
b0 %
0$
0#
0"
0!
$end
#10
00
0M
0N
1f
0e
0Z
0Y
1T
0S
0g
0[
0U
b1001 %
b1001 2
b1001 K
0`
0_
0c
0W
0Q
0a
1^
b100 O
1\
0.
b100 <
b100 @
b100 I
b1011 9
b1011 ?
b1011 J
b0 &
b0 1
b0 z
1$
1-
15
b0 7
b0 G
b0 y
b0 :
b0 H
b0 x
1|
03
b1011 (
b1011 ,
b1011 >
b1011 B
b1011 F
b100 '
b100 +
b100 =
b100 A
b100 E
0*
#20
0f
1`
0L
1a
0^
0]
b111 %
b111 2
b111 K
1Z
b0 O
1[
1V
b1111 9
b1111 ?
b1111 J
b110 <
b110 @
b110 I
b1111 (
b1111 ,
b1111 >
b1111 B
b1111 F
b110 '
b110 +
b110 =
b110 A
b110 E
#30
10
1e
1L
1_
1M
0Z
1Y
1N
0f
0T
1S
1g
1U
b0 %
b0 2
b0 K
0`
1c
1]
1Q
1a
1W
0\
0V
b1111 O
b0 <
b0 @
b0 I
b100 &
b100 1
b100 z
0$
0-
b0 9
b0 ?
b0 J
05
b1101 7
b1101 G
b1101 y
b110 :
b110 H
b110 x
0|
13
b1101 (
b1101 ,
b1101 >
b1101 B
b1101 F
1*
#40
0!
0"
00
0L
b111 v
0u
b111 w
0q
0f
0e
0_
0M
b0 &
b0 1
b0 z
0g
0a
0[
0U
0Z
0Y
b1000 8
b1000 C
b1000 i
1#
b1000 ;
b1000 D
b1000 h
0c
0]
0W
0Q
0N
14
b0 7
b0 G
b0 y
b0 :
b0 H
b0 x
b0 O
b0 %
b0 2
b0 K
0T
0S
1{
03
b1000 (
b1000 ,
b1000 >
b1000 B
b1000 F
b1000 '
b1000 +
b1000 =
b1000 A
b1000 E
0)
#50
1$
1.
10
1L
1d
1^
1f
0`
b1001 %
b1001 2
b1001 K
1T
1c
1]
0g
0a
1U
b1100 O
1b
1\
1P
b1101 <
b1101 @
b1101 I
b1100 9
b1100 ?
b1100 J
b1111 v
b1111 w
1-
16
b0 8
b0 C
b0 i
b0 ;
b0 D
b0 h
0#
1|
04
b1100 (
b1100 ,
b1100 >
b1100 B
b1100 F
b1101 '
b1101 +
b1101 =
b1101 A
b1101 E
0*
#60
1e
1_
0f
1M
0$
10
0`
1L
1Y
0.
0b
0\
0P
1g
0d
1a
0^
1[
1U
0R
0Z
0-
b0 9
b0 ?
b0 J
b0 <
b0 @
b0 I
1c
1]
1W
1Q
1N
06
0#
b1111 O
b0 %
b0 2
b0 K
0T
1S
0{
0|
04
13
b0 (
b0 ,
b0 >
b0 B
b0 F
b0 '
b0 +
b0 =
b0 A
b0 E
1)
1*
#70
1`
00
0L
0$
1V
1P
1f
0e
0_
0M
0.
b11 <
b11 @
b11 I
b1100 9
b1100 ?
b1100 J
1g
1a
1[
1U
1Z
0Y
1-
1c
1]
0W
0Q
0N
16
b1100 O
b1111 %
b1111 2
b1111 K
1T
0S
1{
1|
03
b1100 (
b1100 ,
b1100 >
b1100 B
b1100 F
b11 '
b11 +
b11 =
b11 A
b11 E
0)
0*
#80
10
1e
1L
0`
1_
0V
0P
0!
1/
0n
0"
0f
1M
0s
b1111 v
0u
1j
0o
b1111 w
0q
b1010 &
b1010 1
b1010 z
0b
1g
1a
1[
0X
1U
0R
0Z
1Y
0-
b0 9
b0 ?
b0 J
b0 <
b0 @
b0 I
1c
1]
1W
1Q
1N
06
b0 8
b0 C
b0 i
b0 ;
b0 D
b0 h
0#
b1010 7
b1010 G
b1010 y
b1011 :
b1011 H
b1011 x
b1111 O
b0 %
b0 2
b0 K
0T
1S
0{
0|
04
13
b1010 (
b1010 ,
b1010 >
b1010 B
b1010 F
b1011 '
b1011 +
b1011 =
b1011 A
b1011 E
1)
1*
